gradio_ap_chat_ui/__init__.py
gradio_ap_chat_ui/ap_chat_ui.py
gradio_ap_chat_ui/ap_chat_ui.pyi
gradio_ap_chat_ui/templates/component/Index-BG2POTv1.js
gradio_ap_chat_ui/templates/component/_basePickBy-CdIRZ4ZQ.js
gradio_ap_chat_ui/templates/component/_baseUniq-D2YtIjcT.js
gradio_ap_chat_ui/templates/component/arc-Bx9Xsxql.js
gradio_ap_chat_ui/templates/component/architectureDiagram-SUXI7LT5-1KF4Is23.js
gradio_ap_chat_ui/templates/component/blockDiagram-6J76NXCF-zMofcCQe.js
gradio_ap_chat_ui/templates/component/c4Diagram-6F6E4RAY-C2Q3PLas.js
gradio_ap_chat_ui/templates/component/channel-BzZ0REy3.js
gradio_ap_chat_ui/templates/component/chunk-353BL4L5-B_ooTo1A.js
gradio_ap_chat_ui/templates/component/chunk-67H74DCK-BoVhgPEU.js
gradio_ap_chat_ui/templates/component/chunk-AACKK3MU-D4hgWLdR.js
gradio_ap_chat_ui/templates/component/chunk-BFAMUDN2-DkbYbFFm.js
gradio_ap_chat_ui/templates/component/chunk-E2GYISFI-yRsAzRk-.js
gradio_ap_chat_ui/templates/component/chunk-OW32GOEJ-BAb04QKk.js
gradio_ap_chat_ui/templates/component/chunk-SKB7J2MH-C0DeV_9d.js
gradio_ap_chat_ui/templates/component/chunk-SZ463SBG-Ccd0Th7L.js
gradio_ap_chat_ui/templates/component/classDiagram-M3E45YP4-Db19YdWQ.js
gradio_ap_chat_ui/templates/component/classDiagram-v2-YAWTLIQI-Db19YdWQ.js
gradio_ap_chat_ui/templates/component/clone-n-t7Ge-3.js
gradio_ap_chat_ui/templates/component/cytoscape.esm-CphbmbIK.js
gradio_ap_chat_ui/templates/component/dagre-JOIXM2OF-DS02vJJm.js
gradio_ap_chat_ui/templates/component/defaultLocale-D7EN2tov.js
gradio_ap_chat_ui/templates/component/diagram-5UYTHUR4-BlSoKXS9.js
gradio_ap_chat_ui/templates/component/diagram-VMROVX33-TttR8MAt.js
gradio_ap_chat_ui/templates/component/diagram-ZTM2IBQH-Dh5rMqmx.js
gradio_ap_chat_ui/templates/component/erDiagram-3M52JZNH-2cTNqbHu.js
gradio_ap_chat_ui/templates/component/flowDiagram-KYDEHFYC-B_9iElls.js
gradio_ap_chat_ui/templates/component/ganttDiagram-EK5VF46D-CmyVtBsd.js
gradio_ap_chat_ui-0.0.2.dist-info/METADATA
gradio_ap_chat_ui-0.0.2.dist-info/WHEEL
gradio_ap_chat_ui-0.0.2.dist-info/RECORD
